[
  {
    "relation": [
      "delegate_permission/common.handle_all_urls"
    ],
    "target": {
      "namespace": "android_app",
      "package_name": "com.sarjan.cutoptimizer",
      "sha256_cert_fingerprints": [
        "56:f2:1b:39:ea:a3:02:03:ff:d8:fb:60:49:0c:dd:52:57:b6:a6:d6:15:44:d9:89:66:0c:0e:15:a6:b3:53:d9"
      ]
    }
  },
  {
    "relation": [
      "delegate_permission/common.handle_all_urls"
    ],
    "target": {
      "namespace": "android_app",
      "package_name": "io.github.patelheer305.twa",
      "sha256_cert_fingerprints": [
        "ab:57:32:47:df:68:a4:8b:23:c3:f0:c2:07:5d:75:22:41:64:90:a3:f6:60:99:7a:b3:e1:12:54:1a:6f:7a:28"
      ]
    }
  }
]
